[
    {
        "Question": "Complete the sentence: 'If you don't mind, I would like to ___ a suggestion.'",
        "option_1": "make",
        "option_2": "do",
        "option_3": "give",
        "option_4": "take",
        "Correct_Answer": "make",
        "explanation": "The correct phrase is 'make a suggestion,' which means to offer an idea or proposal.",
        "topic": "Sentence Completion",
        "difficulty": "medium"
    },
    {
        "Question": "Choose the correct word to complete the sentence: 'She was so tired that she ___ asleep immediately.'",
        "option_1": "fell",
        "option_2": "felt",
        "option_3": "fall",
        "option_4": "fallen",
        "Correct_Answer": "fell",
        "explanation": "The correct word is 'fell,' as it is the past tense of 'fall,' which fits the context of the sentence.",
        "topic": "Sentence Completion",
        "difficulty": "medium"
    },
    {
        "Question": "Select the appropriate word to complete the sentence: 'The teacher asked the students to ___ their homework by tomorrow.'",
        "option_1": "submit",
        "option_2": "send",
        "option_3": "give",
        "option_4": "pass",
        "Correct_Answer": "submit",
        "explanation": "The correct word is 'submit,' which means to hand in or present for review.",
        "topic": "Sentence Completion",
        "difficulty": "medium"
    },
    {
        "Question": "Fill in the blank: 'He decided to ___ his old car and buy a new one.'",
        "option_1": "sell",
        "option_2": "buy",
        "option_3": "keep",
        "option_4": "repair",
        "Correct_Answer": "sell",
        "explanation": "The correct word is 'sell,' as it logically follows that he would sell his old car to buy a new one.",
        "topic": "Sentence Completion",
        "difficulty": "medium"
    },
    {
        "Question": "Complete the sentence: 'The meeting was postponed ___ to the bad weather.'",
        "option_1": "due",
        "option_2": "because",
        "option_3": "since",
        "option_4": "as",
        "Correct_Answer": "due",
        "explanation": "The correct phrase is 'due to,' which is used to indicate the cause of something.",
        "topic": "Sentence Completion",
        "difficulty": "medium"
    },
    {
        "Question": "Choose the correct word to complete the sentence: 'She ___ her keys on the table before leaving the house.'",
        "option_1": "left",
        "option_2": "forgot",
        "option_3": "placed",
        "option_4": "lost",
        "Correct_Answer": "left",
        "explanation": "The correct word is 'left,' which means to put something in a place and go away.",
        "topic": "Sentence Completion",
        "difficulty": "medium"
    },
    {
        "Question": "Select the appropriate word to complete the sentence: 'The company plans to ___ its operations to Europe next year.'",
        "option_1": "expand",
        "option_2": "reduce",
        "option_3": "close",
        "option_4": "move",
        "Correct_Answer": "expand",
        "explanation": "The correct word is 'expand,' which means to increase in size or scope.",
        "topic": "Sentence Completion",
        "difficulty": "medium"
    },
    {
        "Question": "Fill in the blank: 'He was ___ to hear the news of his promotion.'",
        "option_1": "excited",
        "option_2": "sad",
        "option_3": "angry",
        "option_4": "worried",
        "Correct_Answer": "excited",
        "explanation": "The correct word is 'excited,' as it conveys a positive reaction to the news of a promotion.",
        "topic": "Sentence Completion",
        "difficulty": "medium"
    },
    {
        "Question": "Complete the sentence: 'The book was so interesting that I couldn't ___ it down.'",
        "option_1": "put",
        "option_2": "take",
        "option_3": "set",
        "option_4": "lay",
        "Correct_Answer": "put",
        "explanation": "The correct phrase is 'put it down,' which means to stop reading or doing something.",
        "topic": "Sentence Completion",
        "difficulty": "medium"
    },
    {
        "Question": "Choose the correct word to complete the sentence: 'They ___ to the party together last night.'",
        "option_1": "went",
        "option_2": "go",
        "option_3": "going",
        "option_4": "gone",
        "Correct_Answer": "went",
        "explanation": "The correct word is 'went,' as it is the past tense of 'go,' which fits the context of the sentence.",
        "topic": "Sentence Completion",
        "difficulty": "medium"
    },
    {
        "Question": "Complete the sentence: 'If I had known about the meeting earlier, I ______ attended.'",
        "option_1": "would have",
        "option_2": "will have",
        "option_3": "would",
        "option_4": "will",
        "Correct_Answer": "would have",
        "explanation": "The sentence is in the past unreal conditional form, which requires 'would have' followed by the past participle of the verb.",
        "topic": "Sentence Completion",
        "difficulty": "medium"
    },
    {
        "Question": "Choose the correct option to complete the sentence: 'She ______ to the gym every day to stay fit.'",
        "option_1": "go",
        "option_2": "goes",
        "option_3": "going",
        "option_4": "gone",
        "Correct_Answer": "goes",
        "explanation": "The sentence is in the present simple tense, which requires the base form of the verb with an -s ending for third person singular subjects.",
        "topic": "Sentence Completion",
        "difficulty": "medium"
    },
    {
        "Question": "Select the correct word to complete the sentence: 'The book was so interesting that I couldn't ______ it down.'",
        "option_1": "put",
        "option_2": "puts",
        "option_3": "putting",
        "option_4": "putted",
        "Correct_Answer": "put",
        "explanation": "The sentence requires the base form of the verb 'put' to complete the phrasal verb 'put down'.",
        "topic": "Sentence Completion",
        "difficulty": "medium"
    },
    {
        "Question": "Fill in the blank: 'He ______ his homework before he went out to play.'",
        "option_1": "finished",
        "option_2": "had finished",
        "option_3": "has finished",
        "option_4": "finishes",
        "Correct_Answer": "had finished",
        "explanation": "The sentence is in the past perfect tense, which is used to indicate that an action was completed before another action in the past.",
        "topic": "Sentence Completion",
        "difficulty": "medium"
    },
    {
        "Question": "Complete the sentence: 'By the time we arrived, the movie ______.'",
        "option_1": "started",
        "option_2": "had started",
        "option_3": "has started",
        "option_4": "starts",
        "Correct_Answer": "had started",
        "explanation": "The sentence is in the past perfect tense, indicating that the movie started before the arrival.",
        "topic": "Sentence Completion",
        "difficulty": "medium"
    },
    {
        "Question": "Choose the correct option to complete the sentence: 'If it ______ tomorrow, we will cancel the picnic.'",
        "option_1": "rains",
        "option_2": "rained",
        "option_3": "will rain",
        "option_4": "would rain",
        "Correct_Answer": "rains",
        "explanation": "The sentence is in the first conditional form, which uses the present simple tense in the if-clause.",
        "topic": "Sentence Completion",
        "difficulty": "medium"
    },
    {
        "Question": "Select the correct word to complete the sentence: 'She ______ her keys on the table before leaving the house.'",
        "option_1": "left",
        "option_2": "leaves",
        "option_3": "leaving",
        "option_4": "had left",
        "Correct_Answer": "left",
        "explanation": "The sentence is in the past simple tense, which requires the past form of the verb 'leave'.",
        "topic": "Sentence Completion",
        "difficulty": "medium"
    },
    {
        "Question": "Fill in the blank: 'The teacher asked the students to ______ their assignments by Friday.'",
        "option_1": "submit",
        "option_2": "submits",
        "option_3": "submitting",
        "option_4": "submitted",
        "Correct_Answer": "submit",
        "explanation": "The sentence requires the base form of the verb 'submit' to complete the infinitive phrase 'to submit'.",
        "topic": "Sentence Completion",
        "difficulty": "medium"
    },
    {
        "Question": "Complete the sentence: 'He was so tired that he ______ asleep as soon as he lay down.'",
        "option_1": "fell",
        "option_2": "falls",
        "option_3": "falling",
        "option_4": "fallen",
        "Correct_Answer": "fell",
        "explanation": "The sentence is in the past simple tense, which requires the past form of the verb 'fall'.",
        "topic": "Sentence Completion",
        "difficulty": "medium"
    },
    {
        "Question": "Choose the correct option to complete the sentence: 'We ______ to the new restaurant if we had known about it earlier.'",
        "option_1": "would have gone",
        "option_2": "will have gone",
        "option_3": "would go",
        "option_4": "will go",
        "Correct_Answer": "would have gone",
        "explanation": "The sentence is in the past unreal conditional form, which requires 'would have' followed by the past participle of the verb.",
        "topic": "Sentence Completion",
        "difficulty": "medium"
    },
    {
        "Question": "Complete the sentence: 'If I had known about the meeting earlier, I ______ attended.'",
        "option_1": "would have",
        "option_2": "will have",
        "option_3": "would",
        "option_4": "will",
        "Correct_Answer": "A",
        "explanation": "The correct answer is 'would have' because the sentence is in the past unreal conditional form, indicating a hypothetical situation that did not happen.",
        "topic": "Sentence Completion",
        "difficulty": "medium"
    },
    {
        "Question": "Choose the correct option to complete the sentence: 'She ______ to the gym every day if she had more time.'",
        "option_1": "goes",
        "option_2": "will go",
        "option_3": "would go",
        "option_4": "went",
        "Correct_Answer": "C",
        "explanation": "The correct answer is 'would go' because the sentence is in the present unreal conditional form, indicating a hypothetical situation that is not currently happening.",
        "topic": "Sentence Completion",
        "difficulty": "medium"
    },
    {
        "Question": "Select the correct word to complete the sentence: 'The book was so interesting that I couldn't ______ it down.'",
        "option_1": "put",
        "option_2": "place",
        "option_3": "set",
        "option_4": "lay",
        "Correct_Answer": "A",
        "explanation": "The correct answer is 'put' because the phrase 'put down' is commonly used to indicate stopping reading a book.",
        "topic": "Sentence Completion",
        "difficulty": "medium"
    },
    {
        "Question": "Fill in the blank: 'If it ______ tomorrow, we will go to the beach.'",
        "option_1": "doesn't rain",
        "option_2": "didn't rain",
        "option_3": "won't rain",
        "option_4": "hadn't rained",
        "Correct_Answer": "A",
        "explanation": "The correct answer is 'doesn't rain' because the sentence is in the first conditional form, indicating a real possibility in the future.",
        "topic": "Sentence Completion",
        "difficulty": "medium"
    },
    {
        "Question": "Complete the sentence: 'He ______ his homework before he went out to play.'",
        "option_1": "finished",
        "option_2": "had finished",
        "option_3": "has finished",
        "option_4": "finishes",
        "Correct_Answer": "B",
        "explanation": "The correct answer is 'had finished' because the action of finishing homework occurred before another past action (going out to play), requiring the past perfect tense.",
        "topic": "Sentence Completion",
        "difficulty": "medium"
    },
    {
        "Question": "Choose the correct option to complete the sentence: 'By the time we arrived, the movie ______.'",
        "option_1": "started",
        "option_2": "had started",
        "option_3": "has started",
        "option_4": "starts",
        "Correct_Answer": "B",
        "explanation": "The correct answer is 'had started' because the action of the movie starting occurred before another past action (our arrival), requiring the past perfect tense.",
        "topic": "Sentence Completion",
        "difficulty": "medium"
    },
    {
        "Question": "Select the correct word to complete the sentence: 'I wish I ______ more time to spend with my family.'",
        "option_1": "have",
        "option_2": "had",
        "option_3": "will have",
        "option_4": "has",
        "Correct_Answer": "B",
        "explanation": "The correct answer is 'had' because the sentence expresses a wish about the present, requiring the past simple tense in this context.",
        "topic": "Sentence Completion",
        "difficulty": "medium"
    },
    {
        "Question": "Fill in the blank: 'She ______ to the party if she had been invited.'",
        "option_1": "would go",
        "option_2": "would have gone",
        "option_3": "will go",
        "option_4": "went",
        "Correct_Answer": "B",
        "explanation": "The correct answer is 'would have gone' because the sentence is in the past unreal conditional form, indicating a hypothetical situation that did not happen.",
        "topic": "Sentence Completion",
        "difficulty": "medium"
    },
    {
        "Question": "Complete the sentence: 'The teacher asked if everyone ______ the assignment.'",
        "option_1": "completed",
        "option_2": "had completed",
        "option_3": "has completed",
        "option_4": "completes",
        "Correct_Answer": "B",
        "explanation": "The correct answer is 'had completed' because the action of completing the assignment occurred before the teacher asked, requiring the past perfect tense.",
        "topic": "Sentence Completion",
        "difficulty": "medium"
    },
    {
        "Question": "Choose the correct option to complete the sentence: 'If you ______ harder, you would have passed the exam.'",
        "option_1": "study",
        "option_2": "studied",
        "option_3": "had studied",
        "option_4": "have studied",
        "Correct_Answer": "C",
        "explanation": "The correct answer is 'had studied' because the sentence is in the past unreal conditional form, indicating a hypothetical situation that did not happen.",
        "topic": "Sentence Completion",
        "difficulty": "medium"
    },
    {
        "Question": "Complete the sentence: 'If I had known about the meeting earlier, I ______ attended.'",
        "option_1": "would have",
        "option_2": "will have",
        "option_3": "would",
        "option_4": "will",
        "Correct_Answer": "would have",
        "explanation": "The correct answer is 'would have' because the sentence is in the past unreal conditional form, indicating a hypothetical situation that did not happen.",
        "topic": "Sentence Completion",
        "difficulty": "medium"
    },
    {
        "Question": "Choose the correct option to complete the sentence: 'She ______ to the gym every day if she had more time.'",
        "option_1": "will go",
        "option_2": "would go",
        "option_3": "goes",
        "option_4": "went",
        "Correct_Answer": "would go",
        "explanation": "The correct answer is 'would go' because the sentence is in the present unreal conditional form, indicating a hypothetical situation that is not currently happening.",
        "topic": "Sentence Completion",
        "difficulty": "medium"
    },
    {
        "Question": "Select the correct word to complete the sentence: 'The book was so interesting that I couldn't ______ it down.'",
        "option_1": "put",
        "option_2": "place",
        "option_3": "set",
        "option_4": "lay",
        "Correct_Answer": "put",
        "explanation": "The correct answer is 'put' because the phrase 'put down' is commonly used to indicate stopping reading a book.",
        "topic": "Sentence Completion",
        "difficulty": "medium"
    },
    {
        "Question": "Fill in the blank: 'If you ______ your homework, you can go out to play.'",
        "option_1": "finish",
        "option_2": "finished",
        "option_3": "will finish",
        "option_4": "are finishing",
        "Correct_Answer": "finish",
        "explanation": "The correct answer is 'finish' because the sentence is in the first conditional form, indicating a real possibility in the future.",
        "topic": "Sentence Completion",
        "difficulty": "medium"
    },
    {
        "Question": "Complete the sentence: 'He ______ his keys before he left the house.'",
        "option_1": "forgot",
        "option_2": "has forgotten",
        "option_3": "had forgotten",
        "option_4": "forgets",
        "Correct_Answer": "had forgotten",
        "explanation": "The correct answer is 'had forgotten' because the action of forgetting the keys happened before he left the house, indicating the past perfect tense.",
        "topic": "Sentence Completion",
        "difficulty": "medium"
    },
    {
        "Question": "Choose the correct option to complete the sentence: 'By the time we arrived, the movie ______.'",
        "option_1": "started",
        "option_2": "had started",
        "option_3": "has started",
        "option_4": "was starting",
        "Correct_Answer": "had started",
        "explanation": "The correct answer is 'had started' because the action of the movie starting happened before the arrival, indicating the past perfect tense.",
        "topic": "Sentence Completion",
        "difficulty": "medium"
    },
    {
        "Question": "Select the correct word to complete the sentence: 'She ______ her phone at home, so she couldn't call for help.'",
        "option_1": "left",
        "option_2": "has left",
        "option_3": "had left",
        "option_4": "was leaving",
        "Correct_Answer": "had left",
        "explanation": "The correct answer is 'had left' because the action of leaving the phone happened before she couldn't call for help, indicating the past perfect tense.",
        "topic": "Sentence Completion",
        "difficulty": "medium"
    },
    {
        "Question": "Fill in the blank: 'If it ______ tomorrow, we will cancel the picnic.'",
        "option_1": "rains",
        "option_2": "rained",
        "option_3": "will rain",
        "option_4": "is raining",
        "Correct_Answer": "rains",
        "explanation": "The correct answer is 'rains' because the sentence is in the first conditional form, indicating a real possibility in the future.",
        "topic": "Sentence Completion",
        "difficulty": "medium"
    },
    {
        "Question": "Complete the sentence: 'They ______ the project by the end of next week.'",
        "option_1": "will finish",
        "option_2": "will have finished",
        "option_3": "are finishing",
        "option_4": "finish",
        "Correct_Answer": "will have finished",
        "explanation": "The correct answer is 'will have finished' because the sentence indicates an action that will be completed by a certain time in the future, using the future perfect tense.",
        "topic": "Sentence Completion",
        "difficulty": "medium"
    },
    {
        "Question": "Choose the correct option to complete the sentence: 'I ______ to the party if I had been invited.'",
        "option_1": "would go",
        "option_2": "would have gone",
        "option_3": "will go",
        "option_4": "went",
        "Correct_Answer": "would have gone",
        "explanation": "The correct answer is 'would have gone' because the sentence is in the past unreal conditional form, indicating a hypothetical situation that did not happen.",
        "topic": "Sentence Completion",
        "difficulty": "medium"
    },
    {
        "Question": "Complete the sentence: 'If I had known about the meeting earlier, I ______ attended.'",
        "option_1": "would have",
        "option_2": "will have",
        "option_3": "had",
        "option_4": "would",
        "Correct_Answer": "would have",
        "explanation": "The correct answer is 'would have' because the sentence is in the past unreal conditional form, indicating a hypothetical situation that did not happen.",
        "topic": "Sentence Completion",
        "difficulty": "medium"
    },
    {
        "Question": "Choose the correct word to complete the sentence: 'She ______ to the store every Saturday.'",
        "option_1": "go",
        "option_2": "goes",
        "option_3": "going",
        "option_4": "gone",
        "Correct_Answer": "goes",
        "explanation": "The correct answer is 'goes' because the sentence is in the simple present tense, and 'she' is a third-person singular subject.",
        "topic": "Sentence Completion",
        "difficulty": "medium"
    },
    {
        "Question": "Fill in the blank: 'The book, ______ I read last night, was very interesting.'",
        "option_1": "that",
        "option_2": "which",
        "option_3": "who",
        "option_4": "whom",
        "Correct_Answer": "which",
        "explanation": "The correct answer is 'which' because it is used to refer to objects or animals, and in this case, it refers to the book.",
        "topic": "Sentence Completion",
        "difficulty": "medium"
    },
    {
        "Question": "Complete the sentence: 'By the time we arrived, the movie ______.'",
        "option_1": "has started",
        "option_2": "had started",
        "option_3": "started",
        "option_4": "starts",
        "Correct_Answer": "had started",
        "explanation": "The correct answer is 'had started' because the past perfect tense is used to indicate an action that was completed before another action in the past.",
        "topic": "Sentence Completion",
        "difficulty": "medium"
    },
    {
        "Question": "Choose the correct word to complete the sentence: 'He ______ his homework before he went out to play.'",
        "option_1": "finish",
        "option_2": "finishes",
        "option_3": "finished",
        "option_4": "has finished",
        "Correct_Answer": "finished",
        "explanation": "The correct answer is 'finished' because the sentence is in the simple past tense, indicating an action that was completed in the past.",
        "topic": "Sentence Completion",
        "difficulty": "medium"
    },
    {
        "Question": "Fill in the blank: 'If it ______ tomorrow, we will cancel the picnic.'",
        "option_1": "rains",
        "option_2": "rained",
        "option_3": "will rain",
        "option_4": "would rain",
        "Correct_Answer": "rains",
        "explanation": "The correct answer is 'rains' because the sentence is in the first conditional form, indicating a real possibility in the future.",
        "topic": "Sentence Completion",
        "difficulty": "medium"
    },
    {
        "Question": "Complete the sentence: 'She ______ to the party if she had been invited.'",
        "option_1": "would go",
        "option_2": "would have gone",
        "option_3": "will go",
        "option_4": "went",
        "Correct_Answer": "would have gone",
        "explanation": "The correct answer is 'would have gone' because the sentence is in the past unreal conditional form, indicating a hypothetical situation that did not happen.",
        "topic": "Sentence Completion",
        "difficulty": "medium"
    },
    {
        "Question": "Choose the correct word to complete the sentence: 'The children ______ playing in the park when it started to rain.'",
        "option_1": "was",
        "option_2": "were",
        "option_3": "is",
        "option_4": "are",
        "Correct_Answer": "were",
        "explanation": "The correct answer is 'were' because 'children' is a plural subject, and the sentence is in the past continuous tense.",
        "topic": "Sentence Completion",
        "difficulty": "medium"
    },
    {
        "Question": "Fill in the blank: 'I ______ to the gym three times a week.'",
        "option_1": "go",
        "option_2": "goes",
        "option_3": "going",
        "option_4": "gone",
        "Correct_Answer": "go",
        "explanation": "The correct answer is 'go' because the sentence is in the simple present tense, and 'I' is a first-person singular subject.",
        "topic": "Sentence Completion",
        "difficulty": "medium"
    },
    {
        "Question": "Complete the sentence: 'They ______ the project by the end of next month.'",
        "option_1": "will finish",
        "option_2": "will have finished",
        "option_3": "finish",
        "option_4": "finished",
        "Correct_Answer": "will have finished",
        "explanation": "The correct answer is 'will have finished' because the future perfect tense is used to indicate an action that will be completed before a specific time in the future.",
        "topic": "Sentence Completion",
        "difficulty": "medium"
    }
]